snakemake_storage_plugin_ftp/__init__.py
snakemake_storage_plugin_ftp-0.1.2.dist-info/LICENSE
snakemake_storage_plugin_ftp-0.1.2.dist-info/METADATA
snakemake_storage_plugin_ftp-0.1.2.dist-info/WHEEL
snakemake_storage_plugin_ftp-0.1.2.dist-info/RECORD
