Metadata-Version: 2.1
Name: snakemake-storage-plugin-ftp
Version: 0.1.2
Summary: A Snakemake plugin for handling input and output via FTP
Home-page: https://github.com/snakemake/snakemake-storage-plugin-ftp
Author: Christopher Tomkins-Tinch
Author-email: tomkinsc@broadinstitute.org
Requires-Python: >=3.11,<4.0
Classifier: Programming Language :: Python :: 3
Classifier: Programming Language :: Python :: 3.11
Classifier: Programming Language :: Python :: 3.12
Requires-Dist: ftputil (>=5.0.4,<6.0.0)
Requires-Dist: snakemake-interface-common (>=1.15.1,<2.0.0)
Requires-Dist: snakemake-interface-storage-plugins (>=3.0.0,<4.0.0)
Project-URL: Documentation, https://snakemake.github.io/snakemake-plugin-catalog/plugins/storage/ftp.html
Project-URL: Repository, https://github.com/snakemake/snakemake-storage-plugin-ftp
